{
  "name": "_janaagency TS",
  "subtitle": "All essentials in one place",
  "iconURL": "https://github.com/janaagency/rp/releases/download/debug/CydiaIcon.png",
  "headerURL": "https://github.com/janaagency/rp/releases/download/debug/CydiaIcon.png",
  "identifier": "_janaagency",
  "sourceURL": "https://raw.githubusercontent.com/janaagency/rp/main/roop/a.json",
  "apps": [
    {
      "name": "LocationSimulator",
      "bundleIdentifier": "com.janaagency.LocationSimulation",
      "developerName": "janaagency",
      "iconURL": "https://github.com/janaagency/rp/releases/download/debug/locsim.png",
      "versions": [
        {
          "version": "1.3.7",
          "date": "2024-01-22",
          "size": 49776043,
          "downloadURL": "https://github.com/janaagency/rp/releases/download/debug/locsim1.3.7.tipa",
          "localizedDescription": "Location spoofer\nLast updated: 01-01-2024\nStatus: \u2705"
        }
      ]
    },
    {
      "name": "palera1n no pc (iOS 15, iPhone 7-X)",
      "bundleIdentifier": "com.janaagency.palera1n15",
      "developerName": "janaagency",
      "iconURL": "https://github.com/janaagency/rp/releases/download/debug/palera1n.png",
      "versions": [
        {
          "version": "1.1.7",
          "date": "2024-01-22",
          "size": 23692891,
          "downloadURL": "https://github.com/janaagency/rp/releases/download/debug/palera1n15.tipa",
          "localizedDescription": "Jailbreak for iOS15 (iPhone 7-X)\nLast updated: 01-22-2024\nStatus: \u2705"
        }
      ]
    },
    {
      "name": "palera1n no pc (iOS 16, iPhone 7-X)",
      "bundleIdentifier": "com.janaagency.palera1n16",
      "developerName": "janaagency",
      "iconURL": "https://github.com/janaagency/rp/releases/download/debug/palera1n.png",
      "versions": [
        {
          "version": "0.999.11",
          "date": "2024-01-21",
          "size": 67105489,
          "downloadURL": "https://github.com/janaagency/rp/releases/download/debug/palera1n16.tipa",
          "localizedDescription": "Jailbreak for iOS16 (iPhone 7-X)\nLast updated: 01-21-2024\nStatus: \u2705"
        }
      ]
    },
    {
      "name": "Taurine (iOS 14.0-14.8.1)",
      "bundleIdentifier": "com.janaagency.taurine",
      "developerName": "janaagency",
      "iconURL": "https://taurine.app/assets/images/icon.png",
      "versions": [
        {
        "version": "1.1.7-3",
        "date": "2023-08-23",
        "size": 32244737,
        "downloadURL": "https://github.com/Odyssey-Team/Taurine/releases/download/1.1.7-3/Taurine_1.1.7-3.ipa",
        "localizedDescription": "Taurine is an iOS 14.0-14.8.1 jailbreak, utilising Procursus and Libhooker\nLast updated: 08-23-2023\nStatus: \u2705"
        }
      ]
    },
    {
      "name": "Dopamine (iOS 15.0-15.4.1, iPhone XS-13)",
      "bundleIdentifier": "com.janaagency.dopamine",
      "developerName": "janaagency",
      "iconURL": "https://ellekit.space/dopamine/assets/icon.png",
      "versions": [
        {
        "version": "1.1.11",
        "date": "2023-10-21",
        "size": 31057172,
        "downloadURL": "https://github.com/opa334/Dopamine/releases/latest/download/Dopamine.tipa",
        "localizedDescription": "Dopamine is an iOS 15.0-15.4.1 jailbreak for (A12-A15,M1)\nLast updated: 10-21-2023\nStatus: \u2705"
        }
      ]
    },
    {
      "name": "Dopamine (Roothide) (iOS 15.0-15.4.1, iPhone XS-13)",
      "bundleIdentifier": "com.janaagency.dopamine-roothide",
      "developerName": "janaagency",
      "iconURL": "https://avatars.githubusercontent.com/u/134120506?v=4",
      "versions": [
        {
        "version": "1.0.7",
        "date": "2023-10-21",
        "size": 34390705,
        "downloadURL": "https://github.com/roothide/Dopamine-roothide/releases/download/1.0.7/Dopamine-RootHide-1.0.7.tipa",
        "localizedDescription": "Dopamine (Roothide) is a completely hidden rootless iOS 15.0-15.4.1 jailbreak for iPhone XS-13\nLast updated: 10-20-2023\nStatus: \u2705"
        }
      ]
    },
    {
      "name": "Bootstrap (Roothide) (iOS 14.0-17.0, iPhone 6-15)",
      "bundleIdentifier": "com.janaagency.bootstrap",
      "developerName": "janaagency",
      "iconURL": "https://raw.githubusercontent.com/roothide/Bootstrap/main/Bootstrap/Assets.xcassets/Bootstrap.imageset/Bootstrap.png",
      "versions": [
        {
        "version": "1.1",
        "date": "2024-01-23",
        "size": 54500455,
        "downloadURL": "https://github.com/m1337v/Bootstrap/releases/download/release/Bootstrap.tipa",
        "localizedDescription": "Bootstrap (Roothide) is a completely hidden rootless iOS 14.0-17.0 jailbreak for iPhone 6-15\nLast updated: 01-23-2024\nStatus: \u2705"
        }
      ]
    },
    {
      "name": "Shadowrocket",
      "bundleIdentifier": "com.janaagency.shadowrocket",
      "developerName": "janaagency",
      "iconURL": "https://www.shadowrocketdownload.com/img/logo.png",
      "versions": [
        {
        "version": "2.2.45",
        "date": "2024-01-23",
        "size": 16769282,
        "downloadURL": "https://github.com/janaagency/rp/releases/download/debug/sr-v2.2.45.tipa",
        "localizedDescription": "Shadowrocket for Proxies\nLast updated: 01-23-2024\nStatus: \u2705"
        }
      ]
    }
  ]
}
